luyiba/__init__.py
luyiba/__main__.py
luyiba/cache_utils.py
luyiba/command_utils.py
luyiba/filter.py
luyiba/utils.py
luyiba/web_utils.py
luyiba-0.5.0.dist-info/licenses/LICENSE
luyiba-0.5.0.dist-info/METADATA
luyiba-0.5.0.dist-info/WHEEL
luyiba-0.5.0.dist-info/entry_points.txt
luyiba-0.5.0.dist-info/top_level.txt
luyiba-0.5.0.dist-info/RECORD
