Metadata-Version: 2.4
Name: luyiba
Version: 0.5.0
Summary: 英雄联盟随机英雄选择器
Home-page: https://github.com/a358003542/luyiba
Author: wander
Author-email: a358003542@outlook.com
Maintainer: wander
Maintainer-email: a358003542@outlook.com
License: MIT
Keywords: python
Classifier: License :: OSI Approved :: MIT License
Classifier: Operating System :: Microsoft
Classifier: Operating System :: POSIX :: Linux
Classifier: Programming Language :: Python :: 3
License-File: LICENSE
Requires-Dist: click
Requires-Dist: diskcache
Requires-Dist: requests
Requires-Dist: my-fake-useragent>=0.2.0
Requires-Dist: pyparsing
Requires-Dist: pywander>=0.8.1
Dynamic: license-file
